amgi_paho_mqtt/__init__.py
amgi_paho_mqtt/py.typed
amgi_paho_mqtt-0.32.0.dist-info/licenses/LICENSE
amgi_paho_mqtt-0.32.0.dist-info/WHEEL
amgi_paho_mqtt-0.32.0.dist-info/entry_points.txt
amgi_paho_mqtt-0.32.0.dist-info/METADATA
amgi_paho_mqtt-0.32.0.dist-info/RECORD
